data_ingestion/aws_services/__init__.py
data_ingestion/aws_services/eventbridge_service.py
data_ingestion/aws_services/s3_service.py
data_ingestion/aws_services/scheduler_service.py
data_ingestion/crud/__init__.py
data_ingestion/crud/data_ingestion_metadata_table/DataIngestionConfig.py
data_ingestion/crud/data_ingestion_metadata_table/ExportStatus.py
data_ingestion/crud/data_ingestion_metadata_table/__init__.py
data_ingestion/database/SetupDB.py
data_ingestion/database/__init__.py
data_ingestion/model/__init__.py
data_ingestion/model/data_ingestion_metadata_table/DataIngestionConfig.py
data_ingestion/model/data_ingestion_metadata_table/ExportStatus.py
data_ingestion/model/data_ingestion_metadata_table/__init__.py
data_ingestion/settings.py
data_ingestion/tests/__init__.py
data_ingestion/tests/aws_services/__init__.py
data_ingestion/tests/aws_services/test_s3_service.py
data_ingestion/tests/aws_services/test_scheduler_service.py
data_ingestion/tests/conftest.py
data_ingestion/tests/crud/__init__.py
data_ingestion/tests/crud/test_data_ingestion_metadata_table.py
data_ingestion/tests/crud/test_export_status.py
data_ingestion/tests/utils/__init__.py
data_ingestion/tests/utils/test_data_ingestion_utils.py
data_ingestion/utils/__init__.py
data_ingestion/utils/aws_session.py
data_ingestion/utils/common.py
data_ingestion/utils/datetime_util.py
data_ingestion/utils/dynamodb_client.py
data_ingestion/utils/eventbridge_client.py
data_ingestion/utils/exception.py
data_ingestion/utils/logger.py
data_ingestion/utils/s3_client.py
data_ingestion/utils/scheduler_client.py
data_ingestion/utils/sqs_client.py
data_ingestion/utils/step_function_client.py
data_ingestion_lib-1.0.3.dist-info/METADATA
data_ingestion_lib-1.0.3.dist-info/WHEEL
data_ingestion_lib-1.0.3.dist-info/RECORD
